streamlit_chartjs/__init__.py
streamlit_chartjs/st_chart_component.py
streamlit_chart_js-0.0.6.dist-info/METADATA
streamlit_chart_js-0.0.6.dist-info/WHEEL
streamlit_chart_js-0.0.6.dist-info/top_level.txt
streamlit_chart_js-0.0.6.dist-info/RECORD
