Metadata-Version: 2.1
Name: streamlit-chart-js
Version: 0.0.6
Summary: A custom component to render Chart.js charts in Streamlit
Home-page: UNKNOWN
Author: Charly Wargnier
Author-email: cwar05@gnail.com
License: UNKNOWN
Platform: UNKNOWN
Classifier: Programming Language :: Python :: 3
Classifier: License :: OSI Approved :: MIT License
Classifier: Operating System :: OS Independent
Requires-Dist: streamlit
